deflex/__init__.py
deflex/analyses.py
deflex/config.py
deflex/creator.ini
deflex/data.py
deflex/deflex.ini
deflex/demand.py
deflex/geometries.py
deflex/main.py
deflex/nodes.py
deflex/postprocessing.py
deflex/results.py
deflex/scenario.py
deflex/scenario_builder.py
deflex/scenario_creator.py
deflex/scenario_tools.py
deflex/tools.py
deflex/transmission.py
deflex/data/geometries/germany_polygon.geojson
deflex/data/geometries/powerlines_labels_de02.geojson
deflex/data/geometries/powerlines_labels_de21.geojson
deflex/data/geometries/powerlines_labels_de22.geojson
deflex/data/geometries/powerlines_lines_de02.geojson
deflex/data/geometries/powerlines_lines_de17.geojson
deflex/data/geometries/powerlines_lines_de21.geojson
deflex/data/geometries/powerlines_lines_de22.geojson
deflex/data/geometries/region_labels_de01.geojson
deflex/data/geometries/region_labels_de02.geojson
deflex/data/geometries/region_labels_de21.geojson
deflex/data/geometries/region_labels_de22.geojson
deflex/data/geometries/region_polygons_de01.geojson
deflex/data/geometries/region_polygons_de02.geojson
deflex/data/geometries/region_polygons_de17.geojson
deflex/data/geometries/region_polygons_de21.geojson
deflex/data/geometries/region_polygons_de22.geojson
deflex/data/static/Zensus2011_Wohnungen.csv
deflex/data/static/decentralised_heat.csv
deflex/data/static/renpass_transmission.csv
deflex/data/static/renpass_transmission_readme.txt
deflex-0.3.0.dist-info/AUTHORS.rst
deflex-0.3.0.dist-info/LICENSE
deflex-0.3.0.dist-info/METADATA
deflex-0.3.0.dist-info/WHEEL
deflex-0.3.0.dist-info/top_level.txt
deflex-0.3.0.dist-info/RECORD
