Metadata-Version: 2.1
Name: deflex
Version: 0.3.0
Summary: deflex - flexible multi-regional energy system model for heat, power and mobility
Home-page: https://github.com/reegis/deflex
Author: Uwe Krien
Author-email: krien@uni-bremen.de
License: MIT
Project-URL: Documentation, https://deflex.readthedocs.io/
Project-URL: Changelog, https://deflex.readthedocs.io/en/latest/changelog.html
Project-URL: Issue Tracker, https://github.com/reegis/deflex/issues
Platform: UNKNOWN
Classifier: Development Status :: 5 - Production/Stable
Classifier: Intended Audience :: Developers
Classifier: License :: OSI Approved :: MIT License
Classifier: Operating System :: Unix
Classifier: Operating System :: POSIX
Classifier: Operating System :: Microsoft :: Windows
Classifier: Programming Language :: Python
Classifier: Programming Language :: Python :: 3.7
Classifier: Programming Language :: Python :: 3.8
Classifier: Programming Language :: Python :: 3.9
Classifier: Topic :: Utilities
Requires-Python: >=3.7
Requires-Dist: oemof.solph (>0.4)
Requires-Dist: oemof.network
Requires-Dist: pandas (>1.0)
Requires-Dist: requests
Requires-Dist: networkx (>2.0)
Requires-Dist: numpy (>=1.19.4)
Requires-Dist: openpyxl (>=1.3.0)
Requires-Dist: dill (>=0.3.3)
Provides-Extra: dev
Requires-Dist: pytest ; extra == 'dev'
Requires-Dist: sphinx ; extra == 'dev'
Requires-Dist: sphinx-rtd-theme ; extra == 'dev'
Requires-Dist: requests ; extra == 'dev'
Requires-Dist: pygeos ; extra == 'dev'
Requires-Dist: geopandas ; extra == 'dev'
Requires-Dist: coveralls ; extra == 'dev'
Requires-Dist: scenario-builder ; extra == 'dev'
Requires-Dist: reegis ; extra == 'dev'
Provides-Extra: dummy
Requires-Dist: oemof ; extra == 'dummy'
Provides-Extra: example
Requires-Dist: matplotlib ; extra == 'example'
Requires-Dist: requests ; extra == 'example'
Requires-Dist: pytz ; extra == 'example'
Provides-Extra: geo
Requires-Dist: pygeos ; extra == 'geo'
Requires-Dist: geopandas ; extra == 'geo'
Requires-Dist: descartes ; extra == 'geo'
Provides-Extra: plot
Requires-Dist: pygraphviz ; extra == 'plot'
Requires-Dist: matplotlib ; extra == 'plot'
Provides-Extra: scenario
Requires-Dist: scenario-builder ; extra == 'scenario'
Requires-Dist: reegis ; extra == 'scenario'
